hyperq-1.0.0.dist-info/RECORD
hyperq-1.0.0.dist-info/METADATA
hyperq-1.0.0.dist-info/top_level.txt
hyperq-1.0.0.dist-info/WHEEL
hyperq-1.0.0.dist-info/licenses/LICENSE
hyperq/hyperq.cpp
hyperq/hyperq.pyx
hyperq/hyperq.cpython-311-x86_64-linux-gnu.so
hyperq/__init__.pyi
hyperq/hyperq.hpp
hyperq/__init__.py
