Metadata-Version: 2.4
Name: hyperq
Version: 1.0.0
Summary: Hyper-fast queue for Python
Author-email: Martin Mkhitaryan <mkhitaryan.martin@2000gmail.com>
License-Expression: MIT
Project-URL: Homepage, https://github.com/martinmkhitaryan/hyperq
Project-URL: Repository, https://github.com/martinmkhitaryan/hyperq
Project-URL: Documentation, https://github.com/martinmkhitaryan/hyperq#readme
Project-URL: Discussions, https://github.com/martinmkhitaryan/hyperq/discussions
Project-URL: Bug Tracker, https://github.com/martinmkhitaryan/hyperq/issues
Keywords: queue,hyper,hyper-queue,hyperqueue,high-performance,inter-process-communication,ipc,shared-memory,ring-buffer,multiprocessing,threading,cython,c++,python,fast,low-latency,concurrent,synchronization,posix,unix,linux,macos
Classifier: Intended Audience :: Developers
Classifier: Programming Language :: Python :: 3
Classifier: Programming Language :: Python :: 3.10
Classifier: Programming Language :: Python :: 3.11
Classifier: Programming Language :: Python :: 3.12
Classifier: Programming Language :: Python :: 3.13
Classifier: Topic :: Software Development :: Libraries :: Python Modules
Requires-Python: >=3.10
License-File: LICENSE
Requires-Dist: cython>=0.29.0
Provides-Extra: test
Requires-Dist: pytest~=8.0; extra == "test"
Requires-Dist: pytest-cov~=6.0; extra == "test"
Requires-Dist: faster-fifo~=1.0; extra == "test"
Requires-Dist: tabulate2~=1.0; extra == "test"
Requires-Dist: numpy~=1.0; extra == "test"
Dynamic: license-file
